portoptpy/__init__.py
portoptpy/client.py
portoptpy-0.1.7.dist-info/LICENSE
portoptpy-0.1.7.dist-info/METADATA
portoptpy-0.1.7.dist-info/WHEEL
portoptpy-0.1.7.dist-info/top_level.txt
portoptpy-0.1.7.dist-info/RECORD
