Metadata-Version: 2.1
Name: portoptpy
Version: 0.1.7
Summary: A Python library for interfacing with the Portfolio Optimizer API: https://docs.portfoliooptimizer.io/
Home-page: https://github.com/autsauce/portoptpy
Author: Maddox Southard
Author-email: maddoxsouthard@yahoo.com
Classifier: Programming Language :: Python :: 3
Classifier: License :: OSI Approved :: MIT License
Classifier: Operating System :: OS Independent
Requires-Python: >=3.6
License-File: LICENSE
Requires-Dist: yfinance
Requires-Dist: requests
Requires-Dist: aiohttp
Requires-Dist: asyncio
Requires-Dist: pandas
Requires-Dist: numpy
